cellpose_vollseg/__init__.py
cellpose_vollseg/__main__.py
cellpose_vollseg/core.py
cellpose_vollseg/dynamics.py
cellpose_vollseg/io.py
cellpose_vollseg/metrics.py
cellpose_vollseg/models.py
cellpose_vollseg/plot.py
cellpose_vollseg/resnet_torch.py
cellpose_vollseg/test_mkl.py
cellpose_vollseg/transforms.py
cellpose_vollseg/utils.py
cellpose_vollseg/version.py
cellpose_vollseg/contrib/__init__.py
cellpose_vollseg/contrib/distributed_segmentation.py
cellpose_vollseg/contrib/openvino_utils.py
cellpose_vollseg/gui/gui.py
cellpose_vollseg/gui/guiparts.py
cellpose_vollseg/gui/io.py
cellpose_vollseg/gui/menus.py
cellpose_vollseg/key/cellpose-data-writer.json
cellpose_vollseg/logo/cellpose.ico
cellpose_vollseg/logo/logo.png
cellpose_vollseg-0.0.3.dist-info/LICENSE
cellpose_vollseg-0.0.3.dist-info/METADATA
cellpose_vollseg-0.0.3.dist-info/WHEEL
cellpose_vollseg-0.0.3.dist-info/entry_points.txt
cellpose_vollseg-0.0.3.dist-info/top_level.txt
cellpose_vollseg-0.0.3.dist-info/RECORD
