Metadata-Version: 2.1
Name: cellpose-vollseg
Version: 0.0.3
Summary: modification of cellpose algorithm
Home-page: https://github.com/MouseLand/cellpose
Author: Varun Kapoor
Author-email: varun.kapoor@kapoorlabs.org
License: BSD
Classifier: Programming Language :: Python :: 3
Classifier: License :: OSI Approved :: BSD License
Classifier: Operating System :: OS Independent
License-File: LICENSE
Requires-Dist: numpy (>=1.20.0)
Requires-Dist: scipy
Requires-Dist: natsort
Requires-Dist: tifffile
Requires-Dist: tqdm
Requires-Dist: numba (>=0.53.0)
Requires-Dist: llvmlite
Requires-Dist: torch (>=1.6)
Requires-Dist: opencv-python-headless
Requires-Dist: fastremap
Requires-Dist: imagecodecs
Provides-Extra: all
Requires-Dist: pyqtgraph (>=0.11.0rc0) ; extra == 'all'
Requires-Dist: pyqt5 ; extra == 'all'
Requires-Dist: pyqt5.sip ; extra == 'all'
Requires-Dist: superqt ; extra == 'all'
Requires-Dist: google-cloud-storage ; extra == 'all'
Requires-Dist: dask ; extra == 'all'
Requires-Dist: dask-image ; extra == 'all'
Requires-Dist: scikit-learn ; extra == 'all'
Provides-Extra: distributed
Requires-Dist: dask ; extra == 'distributed'
Requires-Dist: dask-image ; extra == 'distributed'
Requires-Dist: scikit-learn ; extra == 'distributed'
Provides-Extra: docs
Requires-Dist: sphinx (>=3.0) ; extra == 'docs'
Requires-Dist: sphinxcontrib-apidoc ; extra == 'docs'
Requires-Dist: sphinx-rtd-theme ; extra == 'docs'
Provides-Extra: gui
Requires-Dist: pyqtgraph (>=0.11.0rc0) ; extra == 'gui'
Requires-Dist: pyqt5 ; extra == 'gui'
Requires-Dist: pyqt5.sip ; extra == 'gui'
Requires-Dist: superqt ; extra == 'gui'
Requires-Dist: google-cloud-storage ; extra == 'gui'
